sqlq/__init__.py
sqlq/core.py
sqlq/__metadata__/DISCLIAIMER.md
sqlq/__metadata__/LICENSE
sqlq/__metadata__/README.md
sqlq/__metadata__/__init__.py
sqlq/__metadata__/requirements.txt
sqlq-1.6.0.dist-info/METADATA
sqlq-1.6.0.dist-info/WHEEL
sqlq-1.6.0.dist-info/top_level.txt
sqlq-1.6.0.dist-info/RECORD
